pyLOPE/__init__.py
pyLOPE/utils.py
pyLOPE-0.1.2.dist-info/DESCRIPTION.rst
pyLOPE-0.1.2.dist-info/METADATA
pyLOPE-0.1.2.dist-info/RECORD
pyLOPE-0.1.2.dist-info/WHEEL
pyLOPE-0.1.2.dist-info/metadata.json
pyLOPE-0.1.2.dist-info/top_level.txt
