Metadata-Version: 2.0
Name: pyLOPE
Version: 0.1.2
Summary: A python package for paedological purpose
Home-page: http://github.com/seantyh/pyLOPE
Author: Sean Tseng
Author-email: seantyh@gmail.com
License: MIT
Platform: UNKNOWN
